codec_social_network/LICENSE
codec_social_network/README.MD
codec_social_network/__init__.py
codec_social_network/requirements.txt
codec_social_network/thirdparty.json
codec_social_network-0.10.dist-info/LICENSE.rst
codec_social_network-0.10.dist-info/METADATA
codec_social_network-0.10.dist-info/WHEEL
codec_social_network-0.10.dist-info/top_level.txt
codec_social_network-0.10.dist-info/RECORD
